<?xml version="1.0" encoding="UTF-8"?>
<addons>
<addon id="plugin.video.filmeserialeonlineorg"
       name="Filmeserialeonline.org"
       version="1.0.0"
       provider-name="keddy">
  <requires>
    <import addon="xbmc.python" version="2.1.0"/>
    <import addon="script.module.urlresolver" version="4.0.09"/>
    <import addon="script.mrknow.urlresolver" version="2016.04.06.1"/>
  </requires>
  <extension point="xbmc.python.pluginsource"
            library="default.py">
        <provides>video</provides>
  </extension>
  <extension point="xbmc.addon.metadata">
    <summary>Filme si seriale subtitrate de pe Filmeserialeonline.org</summary>
    <description>Vizioneaza filmele si serialele subtitrate disponibile pe Filmeserialeonline.org</description>
    <platform>all</platform>
    <news>First version</news>
  </extension>
</addon>
<addon id="repository.keddy.repo" name="Keddy's Addons" version="1.0.2" provider-name="keddy">
	<extension point="xbmc.addon.repository" name="Keddy's Addons">
		<info compressed="false">https://raw.githubusercontent.com/keddyboys/keddy-repo/master/addons.xml</info>
		<checksum>https://raw.githubusercontent.com/keddyboys/keddy-repo/master/addons.xml.md5</checksum>
		<datadir zip="true">https://raw.githubusercontent.com/keddyboys/keddy-repo/master/zips</datadir>
	</extension>
	<extension point="xbmc.addon.metadata">
		<summary>Install Addons from https://github.com/keddyboys/keddy-repo</summary>
		<description>Download and install addons for Kodi.</description>
                <disclaimer>Keddy</disclaimer>
		<platform>all</platform>
	</extension>
</addon>
<addon id="plugin.video.triluliluro" name="trilulilu.ro" provider-name="kingul" version="2.0.3">
  <requires>
    <import addon="xbmc.python" version="2.1.0" />
    <import addon="script.common.plugin.cache" version="0.9.1" />
  </requires>
  <extension library="default.py" point="xbmc.python.pluginsource">
        <provides>video</provides>
  </extension>
  <extension point="xbmc.addon.metadata">
    <summary>Filme online de la trilulilu.ro</summary>
    <description>Urmareste videoclipuri de pe trilulilu.ro</description>
    <platform>all</platform>
  </extension>
</addon>
<addon id="plugin.video.220ro" name="220.ro" provider-name="kingul" version="1.0.8">
  <requires>
    <import addon="xbmc.python" version="2.1.0" />
    <import addon="script.common.plugin.cache" version="0.9.1" />
  </requires>
  <extension library="default.py" point="xbmc.python.pluginsource">
        <provides>video</provides>
  </extension>
  <extension point="xbmc.addon.metadata">
    <summary>Videoclipuri de pe 220.ro</summary>
    <description>Urmareste filmulete funny, farse etc de pe 220.ro</description>
    <platform>all</platform>
  </extension>
</addon>
<addon id="plugin.video.protvro" name="Protv.ro" provider-name="kingul" version="1.0.5">
  <requires>
    <import addon="xbmc.python" version="2.1.0" />
    <import addon="script.common.plugin.cache" version="0.9.1" />
  </requires>
  <extension library="default.py" point="xbmc.python.pluginsource">
        <provides>video</provides>
  </extension>
  <extension point="xbmc.addon.metadata">
    <summary>Emisiuni Protv.ro</summary>
    <description>Urmareste emisiunile si serialele difuzate pe ProTV</description>
    <platform>all</platform>
  </extension>
</addon>
<addon id="plugin.video.tvrplus" name="TvrPlus" provider-name="kingul" version="1.0.3">
  <requires>
    <import addon="xbmc.python" version="2.1.0" />
    <import addon="script.common.plugin.cache" version="0.9.1" />
  </requires>
  <extension library="default.py" point="xbmc.python.pluginsource">
        <provides>video</provides>
  </extension>
  <extension point="xbmc.addon.metadata">
    <summary>Emisiuni TvrPlus</summary>
    <description>Urmareste emisiunile aflate pe TvrPlus.ro</description>
    <platform>all</platform>
  </extension>
</addon>
<addon id="plugin.video.digi24" name="Digi24" provider-name="kingul" version="1.1.5">
  <requires>
    <import addon="xbmc.python" version="2.1.0" />
    <import addon="script.common.plugin.cache" version="0.9.1" />
  </requires>
  <extension library="default.py" point="xbmc.python.pluginsource">
        <provides>video</provides>
  </extension>
  <extension point="xbmc.addon.metadata">
    <summary>Emisiuni digi24</summary>
    <description>Urmareste emisiunile aflate pe Digi24.ro</description>
    <platform>all</platform>
  </extension>
</addon>
<addon id="service.subtitles.regielive" name="Regielive" provider-name="kingul" version="1.0.7">
  <requires>
    <import addon="xbmc.python" version="2.1.0" />
  </requires>
  <extension library="service.py" point="xbmc.subtitle.module" />
  <extension point="xbmc.addon.metadata">
    <summary lang="en">Regielive</summary>
    <description lang="en">Cauta si descarca subtitrari de pe subtitrari.regielive.ro</description>
    <disclaimer lang="en" />
    <platform>all</platform>
    <license>GNU GENERAL PUBLIC LICENSE. Version 2, June 1991</license>
    <forum>http://forum.xbmc.org/showthread.php?tid=183114</forum>
    <website />
    <email />
    <source>https://github.com/viorel-m/kodi-repo</source>    
  </extension>
</addon>
<addon id="service.subtitles.subsro" name="Subs.ro" provider-name="kingul" version="1.1.0">
  <requires>
    <import addon="xbmc.python" version="2.1.0" />
  </requires>
  <extension library="service.py" point="xbmc.subtitle.module" />
  <extension point="xbmc.addon.metadata">
    <summary lang="en">Subs.ro</summary>
    <description lang="en">Cauta si descarca subtitrari de pe subs.ro</description>
    <disclaimer lang="en" />
    <platform>all</platform>
    <license>GNU GENERAL PUBLIC LICENSE. Version 2, June 1991</license>
    <forum>http://forum.xbmc.org/showthread.php?tid=183114</forum>
    <website />
    <email />
    <source>https://github.com/viorel-m/kodi-repo</source>    
  </extension>
</addon>
<addon id="service.subtitles.titrariro" name="Titrari.ro" provider-name="kingul" version="1.0.7">
  <requires>
    <import addon="xbmc.python" version="2.1.0" />
  </requires>
  <extension library="service.py" point="xbmc.subtitle.module" />
  <extension point="xbmc.addon.metadata">
    <summary lang="en">Titrari.ro</summary>
    <description lang="en">Cauta si descarca subtitrari de pe titrari.ro</description>
    <disclaimer lang="en" />
    <platform>all</platform>
    <license>GNU GENERAL PUBLIC LICENSE. Version 2, June 1991</license>
    <forum>http://forum.xbmc.org/showthread.php?tid=183114</forum>
    <website />
    <email />
    <source>https://github.com/viorel-m/kodi-repo</source>    
  </extension>
</addon>
<addon id="service.subtitles.subtitrarinoiro" name="Subtitrari-noi.ro" provider-name="kingul" version="1.0.7">
  <requires>
    <import addon="xbmc.python" version="2.1.0" />
  </requires>
  <extension library="service.py" point="xbmc.subtitle.module" />
  <extension point="xbmc.addon.metadata">
    <summary lang="en">Subtitrari-noi.ro</summary>
    <description lang="en">Cauta si descarca subtitrari de pe subtitrari-noi.ro</description>
    <disclaimer lang="en" />
    <platform>all</platform>
    <license>GNU GENERAL PUBLIC LICENSE. Version 2, June 1991</license>
    <forum>http://forum.xbmc.org/showthread.php?tid=183114</forum>
    <website />
    <email />
    <source>https://github.com/viorel-m/kodi-repo</source>    
  </extension>
</addon>
<addon id="plugin.video.tvrplus"
       name="TvrPlus"
       version="1.0.4"
       provider-name="kingul">
  <requires>
    <import addon="xbmc.python" version="2.1.0"/>
  </requires>
  <extension point="xbmc.python.pluginsource"
            library="default.py">
        <provides>video</provides>
  </extension>
  <extension point="xbmc.addon.metadata">
    <summary>Emisiuni TvrPlus</summary>
    <description>Urmareste emisiunile aflate pe TvrPlus.ro</description>
    <platform>all</platform>
  </extension>
</addon>
<addon id="plugin.video.tvmaniabgcom"
       name="TVManiaBG.com"
       version="1.0.0"
       provider-name="kingul">
  <requires>
    <import addon="xbmc.python" version="2.1.0"/>
  </requires>
  <extension point="xbmc.python.pluginsource"
            library="default.py">
        <provides>video</provides>
  </extension>
  <extension point="xbmc.addon.metadata">
    <summary>Live video from TvManiaBG.com</summary>
    <description>Watch live streaming video from TvManiaBG.com</description>
    <platform>all</platform>
  </extension>
</addon>
<addon id="plugin.video.protvro"
       name="Protv.ro"
       version="1.1.0"
       provider-name="kingul">
  <requires>
    <import addon="xbmc.python" version="2.1.0"/>
  </requires>
  <extension point="xbmc.python.pluginsource"
            library="default.py">
        <provides>video</provides>
  </extension>
  <extension point="xbmc.addon.metadata">
    <summary>Emisiuni Protv.ro</summary>
    <description>Urmareste emisiunile si serialele difuzate pe ProTV</description>
    <platform>all</platform>
  </extension>
</addon>

<addon id="plugin.video.klatvro"
       name="Kla.tv"
       version="1.0.3"
       provider-name="kingul">
  <requires>
    <import addon="xbmc.python" version="2.1.0"/>
  </requires>
  <extension point="xbmc.python.pluginsource"
            library="default.py">
        <provides>video</provides>
  </extension>
  <extension point="xbmc.addon.metadata">
    <summary>Video de pe kla.tv</summary>
    <description>Vizualizeaza videoclipuri de pe kla.tv</description>
    <platform>all</platform>
  </extension>
</addon>

<addon id="plugin.video.filmehdnet"
       name="FilmeHD.net"
       version="1.0.4"
       provider-name="kingul">
  <requires>
    <import addon="xbmc.python" version="2.1.0"/>
    <import addon="script.module.urlresolver" version="3.0.0"/>
  </requires>
  <extension point="xbmc.python.pluginsource"
            library="default.py">
        <provides>video</provides>
  </extension>
  <extension point="xbmc.addon.metadata">
    <summary>Filme de pe FilmeHD.net</summary>
    <description>Urmareste filme subtitrate in romana de pe FilmeHD.net</description>
    <platform>all</platform>
  </extension>
</addon>
<addon id="plugin.video.moviereleases" name="Movie Releases" version="0.2.8e" provider-name="Mafarricos, forked by Kingul">
  <requires>
    <import addon="xbmc.python" version="2.14.0"/>
	<import addon="script.module.beautifulsoup" version="3.2.1"/>
	<import addon="script.module.metahandler" version="2.7.0"/>
	<import addon="plugin.video.youtube" version="1.0.0"/>
        <import addon="plugin.video.torrenter" version="2.6.1"/>
	<import addon="script.module.addonsresolver" optional="true"/>
  </requires>
  <extension point="xbmc.python.pluginsource" library="main.py">
    <provides>video</provides>
  </extension>
  <extension point="xbmc.addon.metadata">
    <language>en</language>
    <platform>all</platform>
    <summary lang="en">Movie Releases</summary>
    <description lang="en">Various movie sources to check what's trending, Upcoming, Releases. (Sources from trakt, rotten tomatoes, IMDB, TMDB)</description>
    <platform>all</platform>
    <news>fix dependency</news>
  </extension>
</addon>
<addon id="service.subtitles.addic7ed"
       name="Addic7ed.com"
       version="1.1.1f"
       provider-name="CFlannagan, forked by Kingul">
    <requires>
        <import addon="xbmc.python" version="2.14.0"/>
    </requires>
    <extension point="xbmc.subtitle.module"
               library="service.py"/>
    <extension point="xbmc.addon.metadata">
        <summary lang="en">Get subtitles from Addic7ed.com</summary>
        <description lang="en">Description for Addic7ed to come</description>
        <disclaimer lang="en"/>
        <platform>all</platform>
        <language/>
        <license>GNU GENERAL PUBLIC LICENSE. Version 2, June 1991</license>
        <forum>http://forum.xbmc.org/showthread.php?tid=184854</forum>
        <website/>
        <email/>
        <source>https://github.com/cflannagan/service.subtitles.addic7ed</source>
    </extension>
</addon>

<addon id="service.subtitles.subsro"
       name="Subs.ro"
       version="1.1.3"
       provider-name="kingul">
  <requires>
    <import addon="xbmc.python" version="2.1.0"/>
  </requires>
  <extension point="xbmc.subtitle.module"
             library="service.py" />
  <extension point="xbmc.addon.metadata">
    <summary lang="en">Subs.ro</summary>
    <description lang="en">Cauta si descarca subtitrari de pe subs.ro</description>
    <disclaimer lang="en"></disclaimer>
    <platform>all</platform>
    <license>GNU GENERAL PUBLIC LICENSE. Version 2, June 1991</license>
    <forum>http://forum.xbmc.org/showthread.php?tid=183114</forum>
    <website></website>
    <email></email>
    <source>https://github.com/viorel-m/kingul-repo</source>
  </extension>
</addon>

<addon id="service.subtitles.titrariro"
       name="Titrari.ro"
       version="1.1.1"
       provider-name="kingul">
  <requires>
    <import addon="xbmc.python" version="2.1.0"/>
  </requires>
  <extension point="xbmc.subtitle.module"
             library="service.py" />
  <extension point="xbmc.addon.metadata">
    <summary lang="en">Titrari.ro</summary>
    <description lang="en">Cauta si descarca subtitrari de pe titrari.ro</description>
    <disclaimer lang="en"></disclaimer>
    <platform>all</platform>
    <license>GNU GENERAL PUBLIC LICENSE. Version 2, June 1991</license>
    <forum>http://forum.xbmc.org/showthread.php?tid=183114</forum>
    <website></website>
    <email></email>
    <source>https://github.com/viorel-m/kodi-repo</source>
    <news>Small fixes</news>
  </extension>
</addon>

<addon id="plugin.video.triluliluro"
       name="trilulilu.ro"
       version="2.0.4"
       provider-name="kingul">
  <requires>
    <import addon="xbmc.python" version="2.1.0"/>
  </requires>
  <extension point="xbmc.python.pluginsource"
            library="default.py">
        <provides>video</provides>
  </extension>
  <extension point="xbmc.addon.metadata">
    <summary>Filme online de la trilulilu.ro</summary>
    <description>Urmareste videoclipuri de pe trilulilu.ro</description>
    <platform>all</platform>
  </extension>
</addon>

<addon id="plugin.video.filmeonline2013biz"
       name="Filmeonline2013.biz"
       version="1.0.6"
       provider-name="kingul">
  <requires>
    <import addon="xbmc.python" version="2.1.0"/>
    <import addon="script.module.urlresolver"  version="3.0.0"/>
  </requires>
  <extension point="xbmc.python.pluginsource"
            library="default.py">
        <provides>video</provides>
  </extension>
  <extension point="xbmc.addon.metadata">
    <summary>Filme de pe filmeonline2013.biz</summary>
    <description>Urmareste filme subtitrate in romana de pe filmeonline2013.biz</description>
    <platform>all</platform>
  </extension>
</addon>

<addon id="service.subtitles.subtitrarinoiro"
       name="Subtitrari-noi.ro"
       version="1.0.9"
       provider-name="kingul">
  <requires>
    <import addon="xbmc.python" version="2.1.0"/>
  </requires>
  <extension point="xbmc.subtitle.module"
             library="service.py" />
  <extension point="xbmc.addon.metadata">
    <summary lang="en">Subtitrari-noi.ro</summary>
    <description lang="en">Cauta si descarca subtitrari de pe subtitrari-noi.ro</description>
    <disclaimer lang="en"></disclaimer>
    <platform>all</platform>
    <license>GNU GENERAL PUBLIC LICENSE. Version 2, June 1991</license>
    <forum>http://forum.xbmc.org/showthread.php?tid=183114</forum>
    <website></website>
    <email></email>
    <source>https://github.com/viorel-m/kodi-repo</source>
  </extension>
</addon>

<addon id="plugin.video.hindilovercom"
       name="Hindilover.com"
       version="1.1.7"
       provider-name="kingul">
  <requires>
    <import addon="xbmc.python" version="2.1.0"/>
    <import addon="script.module.urlresolver" version="3.0.0"/>
  </requires>
  <extension point="xbmc.python.pluginsource"
            library="default.py">
        <provides>video</provides>
  </extension>
  <extension point="xbmc.addon.metadata">
    <summary>Seriale si filme hindilover.com</summary>
    <description>Urmareste seriale si filme de pe hindilover.com</description>
    <platform>all</platform>
    <news>small fixes</news>
  </extension>
</addon>

<addon id="plugin.video.desene3dcom"
       name="Desene3d.com"
       version="1.0.5"
       provider-name="kingul">
  <requires>
    <import addon="xbmc.python" version="2.1.0"/>
    <import addon="script.module.urlresolver" version="3.0.0"/>
  </requires>
  <extension point="xbmc.python.pluginsource"
            library="default.py">
        <provides>video</provides>
  </extension>
  <extension point="xbmc.addon.metadata">
    <summary>continut video Deseneanimate3D.com</summary>
    <description>vizioneaza filme, seriale, emisiuni tv si altele, subtitrate sau dublate in limba romana</description>
    <platform>all</platform>
    <news>mici reparatii</news>
  </extension>
</addon>

<addon id="plugin.video.filmeonlinebiz"
       name="FilmeOnline.biz"
       version="1.0.2"
       provider-name="kingul">
  <requires>
    <import addon="xbmc.python" version="2.1.0"/>
    <import addon="script.module.urlresolver" version="3.0.0"/>
    <import addon="script.mrknow.urlresolver" version="2016.04.06.1"/>
  </requires>
  <extension point="xbmc.python.pluginsource"
            library="default.py">
        <provides>video</provides>
  </extension>
  <extension point="xbmc.addon.metadata">
    <summary>Filme subtitrate de pe FilmeOnline.biz</summary>
    <description>Vizioneaza filmele subtitrate disponibile pe FilmeOnline.biz</description>
    <platform>all</platform>
    <news>small fixes</news>
  </extension>
</addon>
</addons>